odoo/addons/web_favicon/README.rst
odoo/addons/web_favicon/__init__.py
odoo/addons/web_favicon/__manifest__.py
odoo/addons/web_favicon/i18n/it.po
odoo/addons/web_favicon/i18n/web_favicon.pot
odoo/addons/web_favicon/models/__init__.py
odoo/addons/web_favicon/models/res_company.py
odoo/addons/web_favicon/readme/CONFIGURE.md
odoo/addons/web_favicon/readme/CONTRIBUTORS.md
odoo/addons/web_favicon/readme/DESCRIPTION.md
odoo/addons/web_favicon/readme/ROADMAP.md
odoo/addons/web_favicon/static/description/icon.png
odoo/addons/web_favicon/static/description/index.html
odoo/addons/web_favicon/tests/__init__.py
odoo/addons/web_favicon/tests/test_web_favicon.py
odoo/addons/web_favicon/views/res_company_views.xml
odoo/addons/web_favicon/views/templates.xml
odoo_addon_web_favicon-19.0.1.0.0.2.dist-info/METADATA
odoo_addon_web_favicon-19.0.1.0.0.2.dist-info/WHEEL
odoo_addon_web_favicon-19.0.1.0.0.2.dist-info/top_level.txt
odoo_addon_web_favicon-19.0.1.0.0.2.dist-info/RECORD
