Metadata-Version: 2.1
Name: odoo-addon-web_favicon
Version: 19.0.1.0.0.2
Requires-Dist: odoo==19.0.*
Summary: Allows to set a custom shortcut icon (aka favicon)
Home-page: https://github.com/OCA/web
License: AGPL-3
Author: Therp BV, Tecnativa, OERP Canada,Odoo Community Association (OCA)
Author-email: support@odoo-community.org
Classifier: Programming Language :: Python
Classifier: Framework :: Odoo
Classifier: Framework :: Odoo :: 19.0
Classifier: License :: OSI Approved :: GNU Affero General Public License v3
